twitter_archive_unshorten.py
twitter_archive_unshorten-0.0.10.dist-info/METADATA
twitter_archive_unshorten-0.0.10.dist-info/WHEEL
twitter_archive_unshorten-0.0.10.dist-info/entry_points.txt
twitter_archive_unshorten-0.0.10.dist-info/top_level.txt
twitter_archive_unshorten-0.0.10.dist-info/zip-safe
twitter_archive_unshorten-0.0.10.dist-info/RECORD
