Metadata-Version: 2.1
Name: twitter_archive_unshorten
Version: 0.0.10
Summary: Unshorten the URLs in your Twitter archive
Home-page: https://github.com/docnow/twitter-archive-unshorten
Author: Ed Summers
Author-email: ehs@pobox.com
License: MIT
Requires-Python: >3.5.0
